[
  {
    "inputs": [
      {
        "internalType": "contract IVault",
        "name": "vault",
        "type": "address"
      },
      {
        "internalType": "contract IBalancerMinter",
        "name": "minter",
        "type": "address"
      },
      {
        "internalType": "contract IGatewayRouter",
        "name": "gatewayRouter",
        "type": "address"
      },
      {
        "internalType": "uint64",
        "name": "gasLimit",
        "type": "uint64"
      },
      {
        "internalType": "uint64",
        "name": "gasPrice",
        "type": "uint64"
      },
      {
        "internalType": "uint64",
        "name": "maxSubmissionCost",
        "type": "uint64"
      }
    ],
    "stateMutability": "nonpayable",
    "type": "constructor"
  },
  {
    "anonymous": false,
    "inputs": [
      {
        "indexed": false,
        "internalType": "uint256",
        "name": "gasLimit",
        "type": "uint256"
      },
      {
        "indexed": false,
        "internalType": "uint256",
        "name": "gasPrice",
        "type": "uint256"
      },
      {
        "indexed": false,
        "internalType": "uint256",
        "name": "maxSubmissionCost",
        "type": "uint256"
      }
    ],
    "name": "ArbitrumFeesModified",
    "type": "event"
  },
  {
    "anonymous": false,
    "inputs": [
      {
        "indexed": true,
        "internalType": "address",
        "name": "gauge",
        "type": "address"
      },
      {
        "indexed": true,
        "internalType": "address",
        "name": "recipient",
        "type": "address"
      }
    ],
    "name": "ArbitrumRootGaugeCreated",
    "type": "event"
  },
  {
    "inputs": [
      {
        "internalType": "address",
        "name": "recipient",
        "type": "address"
      }
    ],
    "name": "create",
    "outputs": [
      {
        "internalType": "address",
        "name": "",
        "type": "address"
      }
    ],
    "stateMutability": "nonpayable",
    "type": "function"
  },
  {
    "inputs": [
      {
        "internalType": "bytes4",
        "name": "selector",
        "type": "bytes4"
      }
    ],
    "name": "getActionId",
    "outputs": [
      {
        "internalType": "bytes32",
        "name": "",
        "type": "bytes32"
      }
    ],
    "stateMutability": "view",
    "type": "function"
  },
  {
    "inputs": [],
    "name": "getArbitrumFees",
    "outputs": [
      {
        "internalType": "uint256",
        "name": "gasLimit",
        "type": "uint256"
      },
      {
        "internalType": "uint256",
        "name": "gasPrice",
        "type": "uint256"
      },
      {
        "internalType": "uint256",
        "name": "maxSubmissionCost",
        "type": "uint256"
      }
    ],
    "stateMutability": "view",
    "type": "function"
  },
  {
    "inputs": [],
    "name": "getAuthorizer",
    "outputs": [
      {
        "internalType": "contract IAuthorizer",
        "name": "",
        "type": "address"
      }
    ],
    "stateMutability": "view",
    "type": "function"
  },
  {
    "inputs": [],
    "name": "getGaugeImplementation",
    "outputs": [
      {
        "internalType": "address",
        "name": "",
        "type": "address"
      }
    ],
    "stateMutability": "view",
    "type": "function"
  },
  {
    "inputs": [
      {
        "internalType": "address",
        "name": "gauge",
        "type": "address"
      }
    ],
    "name": "getGaugeRecipient",
    "outputs": [
      {
        "internalType": "address",
        "name": "",
        "type": "address"
      }
    ],
    "stateMutability": "view",
    "type": "function"
  },
  {
    "inputs": [
      {
        "internalType": "address",
        "name": "recipient",
        "type": "address"
      }
    ],
    "name": "getRecipientGauge",
    "outputs": [
      {
        "internalType": "contract ILiquidityGauge",
        "name": "",
        "type": "address"
      }
    ],
    "stateMutability": "view",
    "type": "function"
  },
  {
    "inputs": [],
    "name": "getVault",
    "outputs": [
      {
        "internalType": "contract IVault",
        "name": "",
        "type": "address"
      }
    ],
    "stateMutability": "view",
    "type": "function"
  },
  {
    "inputs": [
      {
        "internalType": "address",
        "name": "gauge",
        "type": "address"
      }
    ],
    "name": "isGaugeFromFactory",
    "outputs": [
      {
        "internalType": "bool",
        "name": "",
        "type": "bool"
      }
    ],
    "stateMutability": "view",
    "type": "function"
  },
  {
    "inputs": [
      {
        "internalType": "uint64",
        "name": "gasLimit",
        "type": "uint64"
      },
      {
        "internalType": "uint64",
        "name": "gasPrice",
        "type": "uint64"
      },
      {
        "internalType": "uint64",
        "name": "maxSubmissionCost",
        "type": "uint64"
      }
    ],
    "name": "setArbitrumFees",
    "outputs": [],
    "stateMutability": "nonpayable",
    "type": "function"
  }
]
