[
  {
    "inputs": [
      {
        "internalType": "contract IAuthorizerAdaptor",
        "name": "authorizerAdaptor",
        "type": "address"
      },
      {
        "internalType": "contract IGaugeAdder",
        "name": "_newGaugeAdder",
        "type": "address"
      },
      {
        "internalType": "contract IGaugeAdder",
        "name": "_oldGaugeAdder",
        "type": "address"
      },
      {
        "internalType": "contract ILiquidityGaugeFactory",
        "name": "_arbitrumRootGaugeFactory",
        "type": "address"
      },
      {
        "internalType": "contract ILiquidityGaugeFactory",
        "name": "_optimismRootGaugeFactory",
        "type": "address"
      },
      {
        "internalType": "address",
        "name": "_liquidityMiningCommitteeMultisig",
        "type": "address"
      },
      {
        "internalType": "address",
        "name": "_gaugeCheckpointingMultisig",
        "type": "address"
      }
    ],
    "stateMutability": "nonpayable",
    "type": "constructor"
  },
  {
    "inputs": [],
    "name": "arbitrumRootGaugeFactory",
    "outputs": [
      {
        "internalType": "contract ILiquidityGaugeFactory",
        "name": "",
        "type": "address"
      }
    ],
    "stateMutability": "view",
    "type": "function"
  },
  {
    "inputs": [],
    "name": "gaugeCheckpointingMultisig",
    "outputs": [
      {
        "internalType": "address",
        "name": "",
        "type": "address"
      }
    ],
    "stateMutability": "view",
    "type": "function"
  },
  {
    "inputs": [],
    "name": "gaugeController",
    "outputs": [
      {
        "internalType": "contract IGaugeController",
        "name": "",
        "type": "address"
      }
    ],
    "stateMutability": "view",
    "type": "function"
  },
  {
    "inputs": [
      {
        "internalType": "bytes4",
        "name": "selector",
        "type": "bytes4"
      }
    ],
    "name": "getActionId",
    "outputs": [
      {
        "internalType": "bytes32",
        "name": "",
        "type": "bytes32"
      }
    ],
    "stateMutability": "view",
    "type": "function"
  },
  {
    "inputs": [],
    "name": "getAuthorizer",
    "outputs": [
      {
        "internalType": "contract IAuthorizer",
        "name": "",
        "type": "address"
      }
    ],
    "stateMutability": "view",
    "type": "function"
  },
  {
    "inputs": [],
    "name": "getAuthorizerAdaptor",
    "outputs": [
      {
        "internalType": "contract IAuthorizerAdaptor",
        "name": "",
        "type": "address"
      }
    ],
    "stateMutability": "view",
    "type": "function"
  },
  {
    "inputs": [],
    "name": "getCurrentStage",
    "outputs": [
      {
        "internalType": "uint256",
        "name": "",
        "type": "uint256"
      }
    ],
    "stateMutability": "view",
    "type": "function"
  },
  {
    "inputs": [
      {
        "internalType": "uint256",
        "name": "stage",
        "type": "uint256"
      }
    ],
    "name": "getStageActivationTime",
    "outputs": [
      {
        "internalType": "uint256",
        "name": "",
        "type": "uint256"
      }
    ],
    "stateMutability": "view",
    "type": "function"
  },
  {
    "inputs": [],
    "name": "getStagesLength",
    "outputs": [
      {
        "internalType": "uint256",
        "name": "",
        "type": "uint256"
      }
    ],
    "stateMutability": "view",
    "type": "function"
  },
  {
    "inputs": [],
    "name": "getVault",
    "outputs": [
      {
        "internalType": "contract IVault",
        "name": "",
        "type": "address"
      }
    ],
    "stateMutability": "view",
    "type": "function"
  },
  {
    "inputs": [],
    "name": "isComplete",
    "outputs": [
      {
        "internalType": "bool",
        "name": "",
        "type": "bool"
      }
    ],
    "stateMutability": "view",
    "type": "function"
  },
  {
    "inputs": [],
    "name": "liquidityMiningCommitteeMultisig",
    "outputs": [
      {
        "internalType": "address",
        "name": "",
        "type": "address"
      }
    ],
    "stateMutability": "view",
    "type": "function"
  },
  {
    "inputs": [],
    "name": "newGaugeAdder",
    "outputs": [
      {
        "internalType": "contract IGaugeAdder",
        "name": "",
        "type": "address"
      }
    ],
    "stateMutability": "view",
    "type": "function"
  },
  {
    "inputs": [],
    "name": "oldGaugeAdder",
    "outputs": [
      {
        "internalType": "contract IGaugeAdder",
        "name": "",
        "type": "address"
      }
    ],
    "stateMutability": "view",
    "type": "function"
  },
  {
    "inputs": [],
    "name": "optimismRootGaugeFactory",
    "outputs": [
      {
        "internalType": "contract ILiquidityGaugeFactory",
        "name": "",
        "type": "address"
      }
    ],
    "stateMutability": "view",
    "type": "function"
  },
  {
    "inputs": [],
    "name": "performNextStage",
    "outputs": [],
    "stateMutability": "nonpayable",
    "type": "function"
  },
  {
    "inputs": [],
    "name": "registerStages",
    "outputs": [],
    "stateMutability": "nonpayable",
    "type": "function"
  }
]