[
  {
    "inputs": [
      {
        "internalType": "contract IVault",
        "name": "vault",
        "type": "address"
      },
      {
        "internalType": "contract IBalancerQueries",
        "name": "queries",
        "type": "address"
      }
    ],
    "stateMutability": "nonpayable",
    "type": "constructor"
  },
  {
    "inputs": [],
    "name": "getPool",
    "outputs": [
      {
        "internalType": "contract ILinearPool",
        "name": "",
        "type": "address"
      }
    ],
    "stateMutability": "view",
    "type": "function"
  },
  {
    "inputs": [
      {
        "internalType": "address",
        "name": "recipient",
        "type": "address"
      }
    ],
    "name": "rebalance",
    "outputs": [
      {
        "internalType": "uint256",
        "name": "",
        "type": "uint256"
      }
    ],
    "stateMutability": "nonpayable",
    "type": "function"
  },
  {
    "inputs": [
      {
        "internalType": "address",
        "name": "recipient",
        "type": "address"
      },
      {
        "internalType": "uint256",
        "name": "extraMain",
        "type": "uint256"
      }
    ],
    "name": "rebalanceWithExtraMain",
    "outputs": [
      {
        "internalType": "uint256",
        "name": "",
        "type": "uint256"
      }
    ],
    "stateMutability": "nonpayable",
    "type": "function"
  }
]