[
  {
    "inputs": [
      {
        "internalType": "contract IAuthorizerAdaptor",
        "name": "adaptor",
        "type": "address"
      }
    ],
    "stateMutability": "nonpayable",
    "type": "constructor"
  },
  {
    "inputs": [
      {
        "internalType": "bytes32",
        "name": "actionId",
        "type": "bytes32"
      },
      {
        "internalType": "address",
        "name": "account",
        "type": "address"
      },
      {
        "internalType": "address",
        "name": "where",
        "type": "address"
      }
    ],
    "name": "canPerform",
    "outputs": [
      {
        "internalType": "bool",
        "name": "",
        "type": "bool"
      }
    ],
    "stateMutability": "view",
    "type": "function"
  },
  {
    "inputs": [
      {
        "internalType": "bytes4",
        "name": "selector",
        "type": "bytes4"
      }
    ],
    "name": "getActionId",
    "outputs": [
      {
        "internalType": "bytes32",
        "name": "",
        "type": "bytes32"
      }
    ],
    "stateMutability": "view",
    "type": "function"
  },
  {
    "inputs": [],
    "name": "getAuthorizer",
    "outputs": [
      {
        "internalType": "contract IAuthorizer",
        "name": "",
        "type": "address"
      }
    ],
    "stateMutability": "view",
    "type": "function"
  },
  {
    "inputs": [],
    "name": "getAuthorizerAdaptor",
    "outputs": [
      {
        "internalType": "contract IAuthorizerAdaptor",
        "name": "",
        "type": "address"
      }
    ],
    "stateMutability": "view",
    "type": "function"
  },
  {
    "inputs": [],
    "name": "getVault",
    "outputs": [
      {
        "internalType": "contract IVault",
        "name": "",
        "type": "address"
      }
    ],
    "stateMutability": "view",
    "type": "function"
  },
  {
    "inputs": [
      {
        "internalType": "address",
        "name": "target",
        "type": "address"
      },
      {
        "internalType": "bytes",
        "name": "data",
        "type": "bytes"
      }
    ],
    "name": "performAction",
    "outputs": [
      {
        "internalType": "bytes",
        "name": "",
        "type": "bytes"
      }
    ],
    "stateMutability": "payable",
    "type": "function"
  }
]